rtl-srcs/utils/tests/memc-sims/memc.v
`timescale 1us / 1us

module memc #(
    parameter ADDR_WIDTH     = 32,
    parameter APP_DATA_WIDTH = 256,
    parameter APP_MASK_WIDTH = 32
) (
    /** DDR phy pins **/
    /* Inouts */
    inout  [31:0] ddr3_dq,
    inout  [ 3:0] ddr3_dqs_n,
    inout  [ 3:0] ddr3_dqs_p,
    /* Outputs */
    output [13:0] ddr3_addr,
    output [ 2:0] ddr3_ba,
    output        ddr3_ras_n,
    output        ddr3_cas_n,
    output        ddr3_we_n,
    output        ddr3_reset_n,
    output [ 0:0] ddr3_ck_p,
    output [ 0:0] ddr3_ck_n,
    output [ 0:0] ddr3_cke,

    output [0:0] ddr3_cs_n,

    output [3:0] ddr3_dm,

    output [0:0] ddr3_odt,
    // Input Clock
    // Differential system clocks
    input        sys_clk_p,
    input        sys_clk_n,
    // differential iodelayctrl clk (reference clock)
    input        clk_ref_p,
    input        clk_ref_n
);
    /**********************************************************************/
    // MEMC USER INTERFACE
    /**********************************************************************/
    reg user_clk=0;
    reg user_rst=0;
	
	// ================================================SIM ONLY
	always #1 user_clk = ~user_clk;
	
	initial begin
		user_rst = 1;
		#10 user_rst = 0;
	end


    /* APP Cmd */
    wire [               2:0] app_cmd;
    wire [    ADDR_WIDTH-1:0] app_addr;
    wire                      app_en;
    /* APP Write */
    wire [APP_DATA_WIDTH-1:0] app_wdf_data;
    wire                      app_wdf_end;
    wire                      app_wdf_wren;
    wire [APP_MASK_WIDTH-1:0] app_wdf_mask;
    /* APP Read */
    wire [APP_DATA_WIDTH-1:0] app_rd_data;
    wire                      app_rd_data_end;


	reg [2:0] cnt1;
	reg [2:0] cnt2;
	always @(posedge user_clk) begin
		cnt1<= (cnt1 == 0)? 4: cnt1-1;
		cnt2<= (cnt2 == 0)? 5: cnt2-1;
	end
    wire app_rdy=(cnt1 != 0);
    wire app_wdf_rdy=(cnt2 != 0);
    reg app_rd_data_valid, rd2;
	reg rd1;
	// assign rd1 = (app_cmd==0) && (app_rdy);
	always @(posedge user_clk) begin
		rd1 <= (app_cmd==0) && (app_rdy);
		rd2 <= rd1;
		app_rd_data_valid <= rd2;
	end

	// ================================================SIM END

    /**********************************************************************/
    // MEMC STATE MACHINE
    /**********************************************************************/
    /* -1- MEMC Status Declartion */
    localparam MEMC_IDLE = 0;
    localparam MEMC_TEST_WR = 1;
    localparam MEMC_TEST_RD = 2;
    // -1.1- MEMC Test Params
    localparam MEMC_TEST_SIZE = 1024;
    localparam MEMC_TEST_START_ADDR = 0;
    localparam MEMC_TEST_END_ADDR = MEMC_TEST_SIZE + MEMC_TEST_START_ADDR;

    // -1.2- MEMC Control
    reg  [ADDR_WIDTH - 1:0] memc_wr_addr = 0;
    reg  [ADDR_WIDTH - 1:0] memc_rd_addr = 0;
    reg  [ADDR_WIDTH - 1:0] app_rd_addr = 0;

    wire                    wdf_rdy;
    assign wdf_rdy = app_rdy & app_wdf_rdy;

    /** -2- MEMC Next status **/
    reg [2:0] state_current = 0;
    reg [2:0] state_next = 0;  // Combinational
    always @(*) begin
        state_next = state_current;
        case (state_current)
            MEMC_IDLE: begin
                state_next = MEMC_TEST_WR;
            end
            MEMC_TEST_WR: begin
                state_next = ((memc_wr_addr == MEMC_TEST_END_ADDR) && (wdf_rdy)) ? MEMC_TEST_RD : MEMC_TEST_WR;
            end
            MEMC_TEST_RD: begin
                state_next = ((app_rd_addr == MEMC_TEST_END_ADDR) && (app_rd_data_valid)) ? MEMC_TEST_WR : MEMC_TEST_RD;
            end
            default: state_next = MEMC_IDLE;
        endcase
    end
    always @(posedge user_clk) begin
        state_current <= (user_rst)? 0: state_next;
    end

    /** -3- MEMC Status Behavior **/
    localparam APP_RD = 0;
    localparam APP_WR = 1;

    /* -3.1- MEMC Wire Assignment  */
    assign app_cmd      = (state_current == MEMC_TEST_WR) ? APP_WR : APP_RD;
    assign app_addr     = (state_current == MEMC_TEST_WR) ? memc_wr_addr : memc_rd_addr;
    assign app_en       = (state_current == MEMC_TEST_WR) || (state_current == MEMC_TEST_RD);

    /* MEMC APP Write */
    assign app_wdf_wren = (state_current == MEMC_TEST_WR) ? 1 : 0;
    assign app_wdf_end  = (state_current == MEMC_TEST_WR) ? 1 : 0;
    assign app_wdf_mask = 0;
    assign app_wdf_data = {8{memc_wr_addr}};


    /*  -3.2- MEMC RD/WR ADDR Control */
    always @(posedge user_clk) begin
        if (state_current == MEMC_TEST_WR) begin
            memc_wr_addr <= (wdf_rdy) ? memc_wr_addr + 8 : memc_wr_addr;
        end else memc_wr_addr <= MEMC_TEST_START_ADDR;
    end
    always @(posedge user_clk) begin
        if (state_current == MEMC_TEST_RD) begin
			if( memc_rd_addr == MEMC_TEST_END_ADDR ) // Reach the end
            	memc_rd_addr <= memc_rd_addr;
			else
            	memc_rd_addr <= (app_rdy) ? memc_rd_addr + 8 : memc_rd_addr;

        end else memc_rd_addr <= MEMC_TEST_START_ADDR;
    end
    always @(posedge user_clk) begin
        // if (app_rd_addr == MEMC_TEST_END_ADDR) begin
            // app_rd_addr <= app_rd_data_valid ? 0 : app_rd_addr;
		if(state_current != MEMC_TEST_RD && state_next == MEMC_TEST_WR) begin
			app_rd_addr <= MEMC_TEST_START_ADDR;
        end else begin
            app_rd_addr <= app_rd_data_valid ? app_rd_addr + 8 : app_rd_addr;
        end
    end

    // Debug Only
    // ila1 ila_inst (
    //     .clk    (user_clk),
    //     .probe1 (app_cmd),
    //     .probe2 (app_en),
    //     .probe3 (app_addr),
    //     .probe4 (app_rdy),
    //     .probe5 (app_rdy),
    //     .probe6 (app_wdf_data),
    //     .probe7 (app_wdf_end),
    //     .probe8 (app_wdf_wren),
    //     .probe9 (app_wdf_mask),
    //     .probe10(app_wdf_rdy),
    //     .probe11(app_rd_data_valid),
    //     .probe12(app_rd_data),
    //     .probe13(app_rd_data_end)
    // );


    /**********************************************************************/
    // MEMC DDR MIG INST
    /**********************************************************************/
    // mig_7series_1 u_mig (
    //     // Memory interface ports
    //     .ddr3_addr          (ddr3_addr),
    //     .ddr3_ba            (ddr3_ba),
    //     .ddr3_cas_n         (ddr3_cas_n),
    //     .ddr3_ck_n          (ddr3_ck_n),
    //     .ddr3_ck_p          (ddr3_ck_p),
    //     .ddr3_cke           (ddr3_cke),
    //     .ddr3_ras_n         (ddr3_ras_n),
    //     .ddr3_we_n          (ddr3_we_n),
    //     .ddr3_dq            (ddr3_dq),
    //     .ddr3_dqs_n         (ddr3_dqs_n),
    //     .ddr3_dqs_p         (ddr3_dqs_p),
    //     .ddr3_reset_n       (ddr3_reset_n),
    //     .init_calib_complete(init_calib_complete),
    //     .ddr3_cs_n          (ddr3_cs_n),
    //     .ddr3_dm            (ddr3_dm),
    //     .ddr3_odt           (ddr3_odt),

    //     // Application interface ports
    //     .app_cmd (app_cmd),
    //     .app_addr(app_addr),
    //     .app_en  (app_en),

    //     .app_wdf_data(app_wdf_data),
    //     .app_wdf_end (app_wdf_end),
    //     .app_wdf_wren(app_wdf_wren),

    //     .app_rd_data      (app_rd_data),
    //     .app_rd_data_end  (app_rd_data_end),
    //     .app_rd_data_valid(app_rd_data_valid),
    //     .app_rdy          (app_rdy),
    //     .app_wdf_rdy      (app_wdf_rdy),
    //     //   .app_sr_active                  (app_sr_active),
    //     //   .app_ref_ack                    (app_ref_ack),
    //     //   .app_zq_ack                     (app_zq_ack),
    //     .ui_clk           (user_clk),
    //     .ui_clk_sync_rst  (rst),

    //     .app_wdf_mask(app_wdf_mask),

    //     .app_sr_req (1'b0),
    //     .app_ref_req(1'b0),
    //     .app_zq_req (1'b0),

    //     // System Clock Ports
    //     .sys_clk_p(sys_clk_p),
    //     .sys_clk_n(sys_clk_n),
    //     // Reference Clock Ports
    //     .clk_ref_p(clk_ref_p),
    //     .clk_ref_n(clk_ref_n),

    //     .sys_rst(sys_rst)
    // );

endmodule  //memc

rtl-srcs/utils/tests/memc-sims/waveform.vcd
$version Generated by VerilatedVcd $end
$timescale 1us $end

 $scope module TOP $end
  $var wire  1 N clk_ref_n $end
  $var wire  1 M clk_ref_p $end
  $var wire 14 ? ddr3_addr [13:0] $end
  $var wire  3 @ ddr3_ba [2:0] $end
  $var wire  1 B ddr3_cas_n $end
  $var wire  1 F ddr3_ck_n [0:0] $end
  $var wire  1 E ddr3_ck_p [0:0] $end
  $var wire  1 G ddr3_cke [0:0] $end
  $var wire  1 H ddr3_cs_n [0:0] $end
  $var wire  4 I ddr3_dm [3:0] $end
  $var wire 32 < ddr3_dq [31:0] $end
  $var wire  4 = ddr3_dqs_n [3:0] $end
  $var wire  4 > ddr3_dqs_p [3:0] $end
  $var wire  1 J ddr3_odt [0:0] $end
  $var wire  1 A ddr3_ras_n $end
  $var wire  1 D ddr3_reset_n $end
  $var wire  1 C ddr3_we_n $end
  $var wire  1 L sys_clk_n $end
  $var wire  1 K sys_clk_p $end
  $scope module memc $end
   $var wire 32 Q ADDR_WIDTH [31:0] $end
   $var wire 32 R APP_DATA_WIDTH [31:0] $end
   $var wire 32 Q APP_MASK_WIDTH [31:0] $end
   $var wire 32 S APP_RD [31:0] $end
   $var wire 32 ] APP_WR [31:0] $end
   $var wire 32 S MEMC_IDLE [31:0] $end
   $var wire 32 _ MEMC_TEST_END_ADDR [31:0] $end
   $var wire 32 ^ MEMC_TEST_RD [31:0] $end
   $var wire 32 _ MEMC_TEST_SIZE [31:0] $end
   $var wire 32 S MEMC_TEST_START_ADDR [31:0] $end
   $var wire 32 ] MEMC_TEST_WR [31:0] $end
   $var wire 32 $ app_addr [31:0] $end
   $var wire  3 # app_cmd [2:0] $end
   $var wire  1 % app_en $end
   $var wire 32 8 app_rd_addr [31:0] $end
   $var wire 256 T app_rd_data [255:0] $end
   $var wire  1 \ app_rd_data_end $end
   $var wire  1 3 app_rd_data_valid $end
   $var wire  1 1 app_rdy $end
   $var wire 256 & app_wdf_data [255:0] $end
   $var wire  1 . app_wdf_end $end
   $var wire 32 S app_wdf_mask [31:0] $end
   $var wire  1 2 app_wdf_rdy $end
   $var wire  1 . app_wdf_wren $end
   $var wire  1 N clk_ref_n $end
   $var wire  1 M clk_ref_p $end
   $var wire  3 / cnt1 [2:0] $end
   $var wire  3 0 cnt2 [2:0] $end
   $var wire 14 ? ddr3_addr [13:0] $end
   $var wire  3 @ ddr3_ba [2:0] $end
   $var wire  1 B ddr3_cas_n $end
   $var wire  1 F ddr3_ck_n [0:0] $end
   $var wire  1 E ddr3_ck_p [0:0] $end
   $var wire  1 G ddr3_cke [0:0] $end
   $var wire  1 H ddr3_cs_n [0:0] $end
   $var wire  4 I ddr3_dm [3:0] $end
   $var wire 32 < ddr3_dq [31:0] $end
   $var wire  4 = ddr3_dqs_n [3:0] $end
   $var wire  4 > ddr3_dqs_p [3:0] $end
   $var wire  1 J ddr3_odt [0:0] $end
   $var wire  1 A ddr3_ras_n $end
   $var wire  1 D ddr3_reset_n $end
   $var wire  1 C ddr3_we_n $end
   $var wire 32 7 memc_rd_addr [31:0] $end
   $var wire 32 6 memc_wr_addr [31:0] $end
   $var wire  1 5 rd1 $end
   $var wire  1 4 rd2 $end
   $var wire  3 : state_current [2:0] $end
   $var wire  3 ; state_next [2:0] $end
   $var wire  1 L sys_clk_n $end
   $var wire  1 K sys_clk_p $end
   $var wire  1 O user_clk $end
   $var wire  1 P user_rst $end
   $var wire  1 9 wdf_rdy $end
  $upscope $end
 $upscope $end
$enddefinitions $end


#0
b000 #
b00000000000000000000000000000000 $
0%
b0000000000000000000000000000000000000000000000000000000000000000000000000000000000000000000000000000000000000000000000000000000000000000000000000000000000000000000000000000000000000000000000000000000000000000000000000000000000000000000000000000000000000000 &
0.
b000 /
b000 0
01
02
03
04
05
b00000000000000000000000000000000 6
b00000000000000000000000000000000 7
b00000000000000000000000000000000 8
09
b000 :
b001 ;
b00000000000000000000000000000000 <
b0000 =
b0000 >
b00000000000000 ?
b000 @
0A
0B
0C
0D
0E
0F
0G
0H
b0000 I
0J
0K
0L
0M
0N
0O
1P
b00000000000000000000000000100000 Q
b00000000000000000000000100000000 R
b00000000000000000000000000000000 S
b0000000000000000000000000000000000000000000000000000000000000000000000000000000000000000000000000000000000000000000000000000000000000000000000000000000000000000000000000000000000000000000000000000000000000000000000000000000000000000000000000000000000000000 T
0\
b00000000000000000000000000000001 ]
b00000000000000000000000000000010 ^
b00000000000000000000010000000000 _
#1
b100 /
b101 0
11
12
19
1O
#2
0O
#3
b011 /
b100 0
15
1O
#4
0O
#5
b010 /
b011 0
14
1O
#6
0O
#7
b001 /
b010 0
13
1O
#8
0O
#9
b000 /
b001 0
01
09
1O
#10
0O
0P
#11
b001 #
1%
1.
b100 /
b000 0
11
02
05
b001 :
1O
#12
0O
#13
b011 /
b101 0
12
04
19
1O
#14
0O
#15
b00000000000000000000000000001000 $
b0000000000000000000000000000100000000000000000000000000000001000000000000000000000000000000010000000000000000000000000000000100000000000000000000000000000001000000000000000000000000000000010000000000000000000000000000000100000000000000000000000000000001000 &
b010 /
b100 0
03
b00000000000000000000000000001000 6
1O
#16
0O
#17
b00000000000000000000000000010000 $
b0000000000000000000000000001000000000000000000000000000000010000000000000000000000000000000100000000000000000000000000000001000000000000000000000000000000010000000000000000000000000000000100000000000000000000000000000001000000000000000000000000000000010000 &
b001 /
b011 0
b00000000000000000000000000010000 6
1O
#18
0O
#19
b00000000000000000000000000011000 $
b0000000000000000000000000001100000000000000000000000000000011000000000000000000000000000000110000000000000000000000000000001100000000000000000000000000000011000000000000000000000000000000110000000000000000000000000000001100000000000000000000000000000011000 &
b000 /
b010 0
01
b00000000000000000000000000011000 6
09
1O
#20
0O
#21
b100 /
b001 0
11
19
1O
#22
0O
#23
b00000000000000000000000000100000 $
b0000000000000000000000000010000000000000000000000000000000100000000000000000000000000000001000000000000000000000000000000010000000000000000000000000000000100000000000000000000000000000001000000000000000000000000000000010000000000000000000000000000000100000 &
b011 /
b000 0
02
b00000000000000000000000000100000 6
09
1O
#24
0O
#25
b010 /
b101 0
12
19
1O
#26
0O
#27
b00000000000000000000000000101000 $
b0000000000000000000000000010100000000000000000000000000000101000000000000000000000000000001010000000000000000000000000000010100000000000000000000000000000101000000000000000000000000000001010000000000000000000000000000010100000000000000000000000000000101000 &
b001 /
b100 0
b00000000000000000000000000101000 6
1O
#28
0O
#29
b00000000000000000000000000110000 $
b0000000000000000000000000011000000000000000000000000000000110000000000000000000000000000001100000000000000000000000000000011000000000000000000000000000000110000000000000000000000000000001100000000000000000000000000000011000000000000000000000000000000110000 &
b000 /
b011 0
01
b00000000000000000000000000110000 6
09
1O
#30
0O
#31
b100 /
b010 0
11
19
1O
#32
0O
#33
b00000000000000000000000000111000 $
b0000000000000000000000000011100000000000000000000000000000111000000000000000000000000000001110000000000000000000000000000011100000000000000000000000000000111000000000000000000000000000001110000000000000000000000000000011100000000000000000000000000000111000 &
b011 /
b001 0
b00000000000000000000000000111000 6
1O
#34
0O
#35
b00000000000000000000000001000000 $
b0000000000000000000000000100000000000000000000000000000001000000000000000000000000000000010000000000000000000000000000000100000000000000000000000000000001000000000000000000000000000000010000000000000000000000000000000100000000000000000000000000000001000000 &
b010 /
b000 0
02
b00000000000000000000000001000000 6
09
1O
#36
0O
#37
b001 /
b101 0
12
19
1O
#38
0O
#39
b00000000000000000000000001001000 $
b0000000000000000000000000100100000000000000000000000000001001000000000000000000000000000010010000000000000000000000000000100100000000000000000000000000001001000000000000000000000000000010010000000000000000000000000000100100000000000000000000000000001001000 &
b000 /
b100 0
01
b00000000000000000000000001001000 6
09
1O
#40
0O
#41
b100 /
b011 0
11
19
1O
#42
0O
#43
b00000000000000000000000001010000 $
b0000000000000000000000000101000000000000000000000000000001010000000000000000000000000000010100000000000000000000000000000101000000000000000000000000000001010000000000000000000000000000010100000000000000000000000000000101000000000000000000000000000001010000 &
b011 /
b010 0
b00000000000000000000000001010000 6
1O
#44
0O
#45
b00000000000000000000000001011000 $
b0000000000000000000000000101100000000000000000000000000001011000000000000000000000000000010110000000000000000000000000000101100000000000000000000000000001011000000000000000000000000000010110000000000000000000000000000101100000000000000000000000000001011000 &
b010 /
b001 0
b00000000000000000000000001011000 6
1O
#46
0O
#47
b00000000000000000000000001100000 $
b0000000000000000000000000110000000000000000000000000000001100000000000000000000000000000011000000000000000000000000000000110000000000000000000000000000001100000000000000000000000000000011000000000000000000000000000000110000000000000000000000000000001100000 &
b001 /
b000 0
02
b00000000000000000000000001100000 6
09
1O
#48
0O
#49
b000 /
b101 0
01
12
1O
#50
0O
#51
b100 /
b100 0
11
19
1O
#52
0O
#53
b00000000000000000000000001101000 $
b0000000000000000000000000110100000000000000000000000000001101000000000000000000000000000011010000000000000000000000000000110100000000000000000000000000001101000000000000000000000000000011010000000000000000000000000000110100000000000000000000000000001101000 &
b011 /
b011 0
b00000000000000000000000001101000 6
1O
#54
0O
#55
b00000000000000000000000001110000 $
b0000000000000000000000000111000000000000000000000000000001110000000000000000000000000000011100000000000000000000000000000111000000000000000000000000000001110000000000000000000000000000011100000000000000000000000000000111000000000000000000000000000001110000 &
b010 /
b010 0
b00000000000000000000000001110000 6
1O
#56
0O
#57
b00000000000000000000000001111000 $
b0000000000000000000000000111100000000000000000000000000001111000000000000000000000000000011110000000000000000000000000000111100000000000000000000000000001111000000000000000000000000000011110000000000000000000000000000111100000000000000000000000000001111000 &
b001 /
b001 0
b00000000000000000000000001111000 6
1O
#58
0O
#59
b00000000000000000000000010000000 $
b0000000000000000000000001000000000000000000000000000000010000000000000000000000000000000100000000000000000000000000000001000000000000000000000000000000010000000000000000000000000000000100000000000000000000000000000001000000000000000000000000000000010000000 &
b000 /
b000 0
01
02
b00000000000000000000000010000000 6
09
1O
#60
0O
#61
b100 /
b101 0
11
12
19
1O
#62
0O
#63
b00000000000000000000000010001000 $
b0000000000000000000000001000100000000000000000000000000010001000000000000000000000000000100010000000000000000000000000001000100000000000000000000000000010001000000000000000000000000000100010000000000000000000000000001000100000000000000000000000000010001000 &
b011 /
b100 0
b00000000000000000000000010001000 6
1O
#64
0O
#65
b00000000000000000000000010010000 $
b0000000000000000000000001001000000000000000000000000000010010000000000000000000000000000100100000000000000000000000000001001000000000000000000000000000010010000000000000000000000000000100100000000000000000000000000001001000000000000000000000000000010010000 &
b010 /
b011 0
b00000000000000000000000010010000 6
1O
#66
0O
#67
b00000000000000000000000010011000 $
b0000000000000000000000001001100000000000000000000000000010011000000000000000000000000000100110000000000000000000000000001001100000000000000000000000000010011000000000000000000000000000100110000000000000000000000000001001100000000000000000000000000010011000 &
b001 /
b010 0
b00000000000000000000000010011000 6
1O
#68
0O
#69
b00000000000000000000000010100000 $
b0000000000000000000000001010000000000000000000000000000010100000000000000000000000000000101000000000000000000000000000001010000000000000000000000000000010100000000000000000000000000000101000000000000000000000000000001010000000000000000000000000000010100000 &
b000 /
b001 0
01
b00000000000000000000000010100000 6
09
1O
#70
0O
#71
b100 /
b000 0
11
02
1O
#72
0O
#73
b011 /
b101 0
12
19
1O
#74
0O
#75
b00000000000000000000000010101000 $
b0000000000000000000000001010100000000000000000000000000010101000000000000000000000000000101010000000000000000000000000001010100000000000000000000000000010101000000000000000000000000000101010000000000000000000000000001010100000000000000000000000000010101000 &
b010 /
b100 0
b00000000000000000000000010101000 6
1O
#76
0O
#77
b00000000000000000000000010110000 $
b0000000000000000000000001011000000000000000000000000000010110000000000000000000000000000101100000000000000000000000000001011000000000000000000000000000010110000000000000000000000000000101100000000000000000000000000001011000000000000000000000000000010110000 &
b001 /
b011 0
b00000000000000000000000010110000 6
1O
#78
0O
#79
b00000000000000000000000010111000 $
b0000000000000000000000001011100000000000000000000000000010111000000000000000000000000000101110000000000000000000000000001011100000000000000000000000000010111000000000000000000000000000101110000000000000000000000000001011100000000000000000000000000010111000 &
b000 /
b010 0
01
b00000000000000000000000010111000 6
09
1O
#80
0O
#81
b100 /
b001 0
11
19
1O
#82
0O
#83
b00000000000000000000000011000000 $
b0000000000000000000000001100000000000000000000000000000011000000000000000000000000000000110000000000000000000000000000001100000000000000000000000000000011000000000000000000000000000000110000000000000000000000000000001100000000000000000000000000000011000000 &
b011 /
b000 0
02
b00000000000000000000000011000000 6
09
1O
#84
0O
#85
b010 /
b101 0
12
19
1O
#86
0O
#87
b00000000000000000000000011001000 $
b0000000000000000000000001100100000000000000000000000000011001000000000000000000000000000110010000000000000000000000000001100100000000000000000000000000011001000000000000000000000000000110010000000000000000000000000001100100000000000000000000000000011001000 &
b001 /
b100 0
b00000000000000000000000011001000 6
1O
#88
0O
#89
b00000000000000000000000011010000 $
b0000000000000000000000001101000000000000000000000000000011010000000000000000000000000000110100000000000000000000000000001101000000000000000000000000000011010000000000000000000000000000110100000000000000000000000000001101000000000000000000000000000011010000 &
b000 /
b011 0
01
b00000000000000000000000011010000 6
09
1O
#90
0O
#91
b100 /
b010 0
11
19
1O
#92
0O
#93
b00000000000000000000000011011000 $
b0000000000000000000000001101100000000000000000000000000011011000000000000000000000000000110110000000000000000000000000001101100000000000000000000000000011011000000000000000000000000000110110000000000000000000000000001101100000000000000000000000000011011000 &
b011 /
b001 0
b00000000000000000000000011011000 6
1O
#94
0O
#95
b00000000000000000000000011100000 $
b0000000000000000000000001110000000000000000000000000000011100000000000000000000000000000111000000000000000000000000000001110000000000000000000000000000011100000000000000000000000000000111000000000000000000000000000001110000000000000000000000000000011100000 &
b010 /
b000 0
02
b00000000000000000000000011100000 6
09
1O
#96
0O
#97
b001 /
b101 0
12
19
1O
#98
0O
#99
b00000000000000000000000011101000 $
b0000000000000000000000001110100000000000000000000000000011101000000000000000000000000000111010000000000000000000000000001110100000000000000000000000000011101000000000000000000000000000111010000000000000000000000000001110100000000000000000000000000011101000 &
b000 /
b100 0
01
b00000000000000000000000011101000 6
09
1O
#100
0O
#101
b100 /
b011 0
11
19
1O
#102
0O
#103
b00000000000000000000000011110000 $
b0000000000000000000000001111000000000000000000000000000011110000000000000000000000000000111100000000000000000000000000001111000000000000000000000000000011110000000000000000000000000000111100000000000000000000000000001111000000000000000000000000000011110000 &
b011 /
b010 0
b00000000000000000000000011110000 6
1O
#104
0O
#105
b00000000000000000000000011111000 $
b0000000000000000000000001111100000000000000000000000000011111000000000000000000000000000111110000000000000000000000000001111100000000000000000000000000011111000000000000000000000000000111110000000000000000000000000001111100000000000000000000000000011111000 &
b010 /
b001 0
b00000000000000000000000011111000 6
1O
#106
0O
#107
b00000000000000000000000100000000 $
b0000000000000000000000010000000000000000000000000000000100000000000000000000000000000001000000000000000000000000000000010000000000000000000000000000000100000000000000000000000000000001000000000000000000000000000000010000000000000000000000000000000100000000 &
b001 /
b000 0
02
b00000000000000000000000100000000 6
09
1O
#108
0O
#109
b000 /
b101 0
01
12
1O
#110
0O
#111
b100 /
b100 0
11
19
1O
#112
0O
#113
b00000000000000000000000100001000 $
b0000000000000000000000010000100000000000000000000000000100001000000000000000000000000001000010000000000000000000000000010000100000000000000000000000000100001000000000000000000000000001000010000000000000000000000000010000100000000000000000000000000100001000 &
b011 /
b011 0
b00000000000000000000000100001000 6
1O
#114
0O
#115
b00000000000000000000000100010000 $
b0000000000000000000000010001000000000000000000000000000100010000000000000000000000000001000100000000000000000000000000010001000000000000000000000000000100010000000000000000000000000001000100000000000000000000000000010001000000000000000000000000000100010000 &
b010 /
b010 0
b00000000000000000000000100010000 6
1O
#116
0O
#117
b00000000000000000000000100011000 $
b0000000000000000000000010001100000000000000000000000000100011000000000000000000000000001000110000000000000000000000000010001100000000000000000000000000100011000000000000000000000000001000110000000000000000000000000010001100000000000000000000000000100011000 &
b001 /
b001 0
b00000000000000000000000100011000 6
1O
#118
0O
#119
b00000000000000000000000100100000 $
b0000000000000000000000010010000000000000000000000000000100100000000000000000000000000001001000000000000000000000000000010010000000000000000000000000000100100000000000000000000000000001001000000000000000000000000000010010000000000000000000000000000100100000 &
b000 /
b000 0
01
02
b00000000000000000000000100100000 6
09
1O
#120
0O
#121
b100 /
b101 0
11
12
19
1O
#122
0O
#123
b00000000000000000000000100101000 $
b0000000000000000000000010010100000000000000000000000000100101000000000000000000000000001001010000000000000000000000000010010100000000000000000000000000100101000000000000000000000000001001010000000000000000000000000010010100000000000000000000000000100101000 &
b011 /
b100 0
b00000000000000000000000100101000 6
1O
#124
0O
#125
b00000000000000000000000100110000 $
b0000000000000000000000010011000000000000000000000000000100110000000000000000000000000001001100000000000000000000000000010011000000000000000000000000000100110000000000000000000000000001001100000000000000000000000000010011000000000000000000000000000100110000 &
b010 /
b011 0
b00000000000000000000000100110000 6
1O
#126
0O
#127
b00000000000000000000000100111000 $
b0000000000000000000000010011100000000000000000000000000100111000000000000000000000000001001110000000000000000000000000010011100000000000000000000000000100111000000000000000000000000001001110000000000000000000000000010011100000000000000000000000000100111000 &
b001 /
b010 0
b00000000000000000000000100111000 6
1O
#128
0O
#129
b00000000000000000000000101000000 $
b0000000000000000000000010100000000000000000000000000000101000000000000000000000000000001010000000000000000000000000000010100000000000000000000000000000101000000000000000000000000000001010000000000000000000000000000010100000000000000000000000000000101000000 &
b000 /
b001 0
01
b00000000000000000000000101000000 6
09
1O
#130
0O
#131
b100 /
b000 0
11
02
1O
#132
0O
#133
b011 /
b101 0
12
19
1O
#134
0O
#135
b00000000000000000000000101001000 $
b0000000000000000000000010100100000000000000000000000000101001000000000000000000000000001010010000000000000000000000000010100100000000000000000000000000101001000000000000000000000000001010010000000000000000000000000010100100000000000000000000000000101001000 &
b010 /
b100 0
b00000000000000000000000101001000 6
1O
#136
0O
#137
b00000000000000000000000101010000 $
b0000000000000000000000010101000000000000000000000000000101010000000000000000000000000001010100000000000000000000000000010101000000000000000000000000000101010000000000000000000000000001010100000000000000000000000000010101000000000000000000000000000101010000 &
b001 /
b011 0
b00000000000000000000000101010000 6
1O
#138
0O
#139
b00000000000000000000000101011000 $
b0000000000000000000000010101100000000000000000000000000101011000000000000000000000000001010110000000000000000000000000010101100000000000000000000000000101011000000000000000000000000001010110000000000000000000000000010101100000000000000000000000000101011000 &
b000 /
b010 0
01
b00000000000000000000000101011000 6
09
1O
#140
0O
#141
b100 /
b001 0
11
19
1O
#142
0O
#143
b00000000000000000000000101100000 $
b0000000000000000000000010110000000000000000000000000000101100000000000000000000000000001011000000000000000000000000000010110000000000000000000000000000101100000000000000000000000000001011000000000000000000000000000010110000000000000000000000000000101100000 &
b011 /
b000 0
02
b00000000000000000000000101100000 6
09
1O
#144
0O
#145
b010 /
b101 0
12
19
1O
#146
0O
#147
b00000000000000000000000101101000 $
b0000000000000000000000010110100000000000000000000000000101101000000000000000000000000001011010000000000000000000000000010110100000000000000000000000000101101000000000000000000000000001011010000000000000000000000000010110100000000000000000000000000101101000 &
b001 /
b100 0
b00000000000000000000000101101000 6
1O
#148
0O
#149
b00000000000000000000000101110000 $
b0000000000000000000000010111000000000000000000000000000101110000000000000000000000000001011100000000000000000000000000010111000000000000000000000000000101110000000000000000000000000001011100000000000000000000000000010111000000000000000000000000000101110000 &
b000 /
b011 0
01
b00000000000000000000000101110000 6
09
1O
#150
0O
#151
b100 /
b010 0
11
19
1O
#152
0O
#153
b00000000000000000000000101111000 $
b0000000000000000000000010111100000000000000000000000000101111000000000000000000000000001011110000000000000000000000000010111100000000000000000000000000101111000000000000000000000000001011110000000000000000000000000010111100000000000000000000000000101111000 &
b011 /
b001 0
b00000000000000000000000101111000 6
1O
#154
0O
#155
b00000000000000000000000110000000 $
b0000000000000000000000011000000000000000000000000000000110000000000000000000000000000001100000000000000000000000000000011000000000000000000000000000000110000000000000000000000000000001100000000000000000000000000000011000000000000000000000000000000110000000 &
b010 /
b000 0
02
b00000000000000000000000110000000 6
09
1O
#156
0O
#157
b001 /
b101 0
12
19
1O
#158
0O
#159
b00000000000000000000000110001000 $
b0000000000000000000000011000100000000000000000000000000110001000000000000000000000000001100010000000000000000000000000011000100000000000000000000000000110001000000000000000000000000001100010000000000000000000000000011000100000000000000000000000000110001000 &
b000 /
b100 0
01
b00000000000000000000000110001000 6
09
1O
#160
0O
#161
b100 /
b011 0
11
19
1O
#162
0O
#163
b00000000000000000000000110010000 $
b0000000000000000000000011001000000000000000000000000000110010000000000000000000000000001100100000000000000000000000000011001000000000000000000000000000110010000000000000000000000000001100100000000000000000000000000011001000000000000000000000000000110010000 &
b011 /
b010 0
b00000000000000000000000110010000 6
1O
#164
0O
#165
b00000000000000000000000110011000 $
b0000000000000000000000011001100000000000000000000000000110011000000000000000000000000001100110000000000000000000000000011001100000000000000000000000000110011000000000000000000000000001100110000000000000000000000000011001100000000000000000000000000110011000 &
b010 /
b001 0
b00000000000000000000000110011000 6
1O
#166
0O
#167
b00000000000000000000000110100000 $
b0000000000000000000000011010000000000000000000000000000110100000000000000000000000000001101000000000000000000000000000011010000000000000000000000000000110100000000000000000000000000001101000000000000000000000000000011010000000000000000000000000000110100000 &
b001 /
b000 0
02
b00000000000000000000000110100000 6
09
1O
#168
0O
#169
b000 /
b101 0
01
12
1O
#170
0O
#171
b100 /
b100 0
11
19
1O
#172
0O
#173
b00000000000000000000000110101000 $
b0000000000000000000000011010100000000000000000000000000110101000000000000000000000000001101010000000000000000000000000011010100000000000000000000000000110101000000000000000000000000001101010000000000000000000000000011010100000000000000000000000000110101000 &
b011 /
b011 0
b00000000000000000000000110101000 6
1O
#174
0O
#175
b00000000000000000000000110110000 $
b0000000000000000000000011011000000000000000000000000000110110000000000000000000000000001101100000000000000000000000000011011000000000000000000000000000110110000000000000000000000000001101100000000000000000000000000011011000000000000000000000000000110110000 &
b010 /
b010 0
b00000000000000000000000110110000 6
1O
#176
0O
